winpwn/__init__.py
winpwn/context.py
winpwn/dbg.py
winpwn/misc.py
winpwn/var.py
winpwn/win.py
winpwn/winpwn.py
padpwn-0.0.1.dist-info/METADATA
padpwn-0.0.1.dist-info/WHEEL
padpwn-0.0.1.dist-info/top_level.txt
padpwn-0.0.1.dist-info/RECORD
