Metadata-Version: 2.1
Name: padpwn
Version: 0.0.1
Summary: mini pwntools for windows
Home-page: UNKNOWN
Author: byzero512
Author-email: byzero512@gamil.com
License: MIT
Platform: UNKNOWN
